
{
  "name": "EXIT",
  "base": "PersistedModel",
  "idInjection": false,
  "options": {
    "validateUpsert": true
  },
  "postgresql": {
    "schema": "v2016",
    "table": "EXIT"
  },
  "properties": {
  "id": {
      "id": true,
      "type": "String",
      "required": false,
      "length": 36,
    },
  "destination" "v2016".destination,
  "exitdate": {
      "type": "Date",
      "required": false
    },
  "otherdestination": {
      "type": "String",
      "required": false,
    },
  "enrollmentid": {
      "type": "String",
      "required": false,
      "length": 36,
    },
  "project_group_code": {
      "type": "String",
      "required": false,
      "length": 8,
    },
  "date_created": {
      "type": "Date",
      "required": false
    },
  "date_created_from_source": {
      "type": "Date",
      "required": false
    },
  "date_updated_from_source": {
      "type": "Date",
      "required": false
    },
  "date_updated": {
      "type": "Date",
      "required": false
    },
  "user_id": {
      "type": "String",
      "required": false,
      "length": 36,
    },
  "export_id": {
      "type": "String",
      "required": false,
      "length": 36,
    },
  "parent_id": {
      "type": "String",
      "required": false,
      "length": 36,
    },
  "version": {
      "type": "Number",
      "required": false,
      "precision": 32,
      "scale": 0
    },
  "source_system_id": {
      "type": "String",
      "required": false,
    },
  "deleted": {
      "type": "Boolean",
      "required": false,
      "default": false
    },
  "active": {
      "type": "Boolean",
      "required": false,
      "default": true
    },
  "sync": {
      "type": "Boolean",
      "required": false,
      "default": false
    },
  CONSTRAINT "exit_enrollmentid_fkey" FOREIGN KEY ("enrollmentid") REFERENCES "v2016".enrollment(id) MATCH SIMPLE ON UPDATE NO action ON DELETE NO action
},
"validations": [],
"relations": {},
"acls": [],
"methods": {}
}
